fast_priority/__init__.py
fast_priority/app.py
fast_priority/cli.py
fast_priority/utils.py
fast_priority-1.1.0.dist-info/entry_points.txt
fast_priority-1.1.0.dist-info/licenses/LICENSE
fast_priority-1.1.0.dist-info/WHEEL
fast_priority-1.1.0.dist-info/METADATA
fast_priority-1.1.0.dist-info/RECORD
