Metadata-Version: 2.4
Name: fast-priority
Version: 1.1.0
Summary: Simple and streigt forward priority queing gateway using fastapi
Keywords: queue,fastapi,priority,redis
Author-email: Korbinian Schweiger <korbinian.schweiger@gmail.com>
Requires-Python: >=3.12
Classifier: Development Status :: 4 - Beta
Classifier: License :: OSI Approved :: MIT License
Classifier: Programming Language :: Python
Classifier: Programming Language :: Python :: 3.12
Classifier: Framework :: FastAPI
Classifier: Intended Audience :: System Administrators
Classifier: Topic :: Internet
License-File: LICENSE
Requires-Dist: fastapi[standard]>=0.115.8
Requires-Dist: httpx
Requires-Dist: python-dotenv>=1.0.1
Requires-Dist: rq>=2.1.0
Requires-Dist: click
Requires-Dist: uvicorn>=0.34.0
